reformer_lm/__init__.py
reformer_lm/attention.py
reformer_lm/broadcasted_dropout.py
reformer_lm/chunk.py
reformer_lm/decoder.py
reformer_lm/gelu.py
reformer_lm/reformer_lm.py
reformer_lm/revnetblock.py
reformer_lm-1.0.1.dist-info/LICENSE
reformer_lm-1.0.1.dist-info/METADATA
reformer_lm-1.0.1.dist-info/WHEEL
reformer_lm-1.0.1.dist-info/top_level.txt
reformer_lm-1.0.1.dist-info/RECORD
