Metadata-Version: 2.1
Name: reformer-lm
Version: 1.0.1
Summary: a Pytorch implementation of the Reformer network (https://openreview.net/forum?id=rkgNKkHtvB)
Home-page: https://github.com/zbloss/reformer_lm
Author: Zachary Bloss
Author-email: zacharybloss@gmail.com
License: UNKNOWN
Keywords: Reformer,ReverseNetwork,Efficient Transformer
Platform: UNKNOWN
Classifier: Programming Language :: Python :: 3
Classifier: License :: OSI Approved :: MIT License
Classifier: Operating System :: OS Independent
Requires-Dist: numpy (>=1.18.0)
Requires-Dist: torch (>=1.3)
